fyipe_sdk/fyipeListener.py
fyipe_sdk/fyipeTransport.py
fyipe_sdk/logger.py
fyipe_sdk/logtype.py
fyipe_sdk/timelineMagager.py
fyipe_sdk/tracker.py
fyipe_sdk/util.py
fyipe_sdk-3.0.13403.dist-info/DESCRIPTION.rst
fyipe_sdk-3.0.13403.dist-info/METADATA
fyipe_sdk-3.0.13403.dist-info/RECORD
fyipe_sdk-3.0.13403.dist-info/WHEEL
fyipe_sdk-3.0.13403.dist-info/metadata.json
fyipe_sdk-3.0.13403.dist-info/top_level.txt
