Metadata-Version: 2.0
Name: fyipe-sdk
Version: 3.0.13403
Summary: A Fyipe package that tracks error event and send logs from your applications to your fyipe dashboard.
Home-page: https://github.com/Fyipe/python-sdk
Author: HackerBay, Inc.
Author-email: hello@hackerbay.io
License: UNKNOWN
Project-URL: Bug Tracker, https://github.com/Fyipe/python-sdk/issues
Platform: UNKNOWN
Classifier: Programming Language :: Python :: 3
Classifier: License :: OSI Approved :: MIT License
Classifier: Operating System :: OS Independent
Requires-Python: >=3.6
License-File: LICENSE
Requires-Dist: requests
Requires-Dist: faker
